dash_blueprint_components_docs/__init__.py
dash_blueprint_components_docs/app.py
dash_blueprint_components_docs/createsrc.py
dash_blueprint_components_docs/utils.py
dash_blueprint_components_docs/wsgi.py
dash_blueprint_components_docs/assets/css/blueprintjsdocs.css
dash_blueprint_components_docs/pages/blueprint/blueprint.py
dash_blueprint_components_docs/pages/blueprint/__pycache__/blueprint.cpython-312.pyc
dash_blueprint_components_docs/pages/blueprint/__pycache__/blueprint.cpython-313.pyc
dash_blueprint_components_docs/pages/blueprint/quickstart/quickstart.py
dash_blueprint_components_docs/pages/blueprint/quickstart/__pycache__/quickstart.cpython-312.pyc
dash_blueprint_components_docs/pages/blueprint/quickstart/__pycache__/quickstart.cpython-313.pyc
dash_blueprint_components_docs/pages/core/core.py
dash_blueprint_components_docs/pages/core/__pycache__/core.cpython-312.pyc
dash_blueprint_components_docs/pages/core/__pycache__/core.cpython-313.pyc
dash_blueprint_components_docs/pages/core/components/components.py
dash_blueprint_components_docs/pages/core/components/__pycache__/components.cpython-312.pyc
dash_blueprint_components_docs/pages/core/components/__pycache__/components.cpython-313.pyc
dash_blueprint_components_docs/pages/core/components/breadcrumb/breadcrumb.py
dash_blueprint_components_docs/pages/core/components/breadcrumb/__pycache__/breadcrumb.cpython-312.pyc
dash_blueprint_components_docs/pages/core/components/breadcrumb/__pycache__/breadcrumb.cpython-313.pyc
dash_blueprint_components_docs/pages/core/components/buttons/buttons.py
dash_blueprint_components_docs/pages/core/components/buttons/__pycache__/buttons.cpython-312.pyc
dash_blueprint_components_docs/pages/core/components/buttons/__pycache__/buttons.cpython-313.pyc
dash_blueprint_components_docs/pages/core/components/callout/callout.py
dash_blueprint_components_docs/pages/core/components/callout/__pycache__/callout.cpython-312.pyc
dash_blueprint_components_docs-0.2.0.dist-info/licenses/LICENSE
dash_blueprint_components_docs-0.2.0.dist-info/METADATA
dash_blueprint_components_docs-0.2.0.dist-info/WHEEL
dash_blueprint_components_docs-0.2.0.dist-info/top_level.txt
dash_blueprint_components_docs-0.2.0.dist-info/RECORD
